helloworld.py
helloworld_test_xz-0.0.1.dist-info/LICENSE.txt
helloworld_test_xz-0.0.1.dist-info/METADATA
helloworld_test_xz-0.0.1.dist-info/WHEEL
helloworld_test_xz-0.0.1.dist-info/top_level.txt
helloworld_test_xz-0.0.1.dist-info/RECORD
