Metadata-Version: 2.1
Name: helloworld-test-xz
Version: 0.0.1
Summary: say hello
Home-page: https://github.com/zxx2643/helloworld
Author: Xiaoxuan Zhang
Author-email: zhangxiaoxuan258@gmail.com
License: UNKNOWN
Platform: UNKNOWN
Classifier: Programming Language :: Python :: 3.6
Classifier: License :: OSI Approved :: GNU Lesser General Public License v3 (LGPLv3)
Requires-Dist: numpy
Provides-Extra: dev
Requires-Dist: pytest (>=3.7) ; extra == 'dev'
